pulumi_wavefront/__init__.py
pulumi_wavefront/_inputs.py
pulumi_wavefront/_utilities.py
pulumi_wavefront/alert.py
pulumi_wavefront/alert_target.py
pulumi_wavefront/cloud_integration_app_dynamics.py
pulumi_wavefront/cloud_integration_aws_external_id.py
pulumi_wavefront/cloud_integration_azure.py
pulumi_wavefront/cloud_integration_azure_activity_log.py
pulumi_wavefront/cloud_integration_cloud_trail.py
pulumi_wavefront/cloud_integration_cloud_watch.py
pulumi_wavefront/cloud_integration_ec2.py
pulumi_wavefront/cloud_integration_gcp.py
pulumi_wavefront/cloud_integration_gcp_billing.py
pulumi_wavefront/cloud_integration_new_relic.py
pulumi_wavefront/dashboard.py
pulumi_wavefront/dashboard_json.py
pulumi_wavefront/derived_metric.py
pulumi_wavefront/event.py
pulumi_wavefront/external_link.py
pulumi_wavefront/get_alert.py
pulumi_wavefront/get_alerts.py
pulumi_wavefront/get_dashboard.py
pulumi_wavefront/get_dashboards.py
pulumi_wavefront/get_default_user_group.py
pulumi_wavefront/get_derived_metric.py
pulumi_wavefront/get_derived_metrics.py
pulumi_wavefront/get_event.py
pulumi_wavefront/get_events.py
pulumi_wavefront/get_external_link.py
pulumi_wavefront/get_external_links.py
pulumi_wavefront/get_maintenance_window.py
pulumi_wavefront/get_maintenance_window_all.py
pulumi_wavefront/get_metrics_policy.py
pulumi_wavefront/get_role.py
pulumi_wavefront/get_roles.py
pulumi_wavefront/get_user.py
pulumi_wavefront/get_user_group.py
pulumi_wavefront/get_user_groups.py
pulumi_wavefront/get_users.py
pulumi_wavefront/ingestion_policy.py
pulumi_wavefront/maintenance_window.py
pulumi_wavefront/metrics_policy.py
pulumi_wavefront/outputs.py
pulumi_wavefront/provider.py
pulumi_wavefront/pulumi-plugin.json
pulumi_wavefront/py.typed
pulumi_wavefront/role.py
pulumi_wavefront/service_account.py
pulumi_wavefront/user.py
pulumi_wavefront/user_group.py
pulumi_wavefront/config/__init__.py
pulumi_wavefront/config/__init__.pyi
pulumi_wavefront/config/vars.py
pulumi_wavefront-3.1.12.dist-info/METADATA
pulumi_wavefront-3.1.12.dist-info/WHEEL
pulumi_wavefront-3.1.12.dist-info/top_level.txt
pulumi_wavefront-3.1.12.dist-info/RECORD
